manilaclient/__init__.py
manilaclient/api_versions.py
manilaclient/base.py
manilaclient/client.py
manilaclient/config.py
manilaclient/exceptions.py
manilaclient/extension.py
manilaclient/shell.py
manilaclient/utils.py
manilaclient/common/__init__.py
manilaclient/common/_i18n.py
manilaclient/common/cliutils.py
manilaclient/common/constants.py
manilaclient/common/httpclient.py
manilaclient/common/apiclient/__init__.py
manilaclient/common/apiclient/exceptions.py
manilaclient/common/apiclient/utils.py
manilaclient/osc/__init__.py
manilaclient/osc/plugin.py
manilaclient/osc/utils.py
manilaclient/osc/v2/__init__.py
manilaclient/osc/v2/availability_zones.py
manilaclient/osc/v2/messages.py
manilaclient/osc/v2/quotas.py
manilaclient/osc/v2/resource_locks.py
manilaclient/osc/v2/security_services.py
manilaclient/osc/v2/services.py
manilaclient/osc/v2/share.py
manilaclient/osc/v2/share_access_rules.py
manilaclient/osc/v2/share_backups.py
manilaclient/osc/v2/share_group_snapshots.py
manilaclient/osc/v2/share_group_type_access.py
manilaclient/osc/v2/share_group_types.py
manilaclient/osc/v2/share_groups.py
manilaclient/osc/v2/share_instance_export_locations.py
manilaclient/osc/v2/share_instances.py
manilaclient/osc/v2/share_limits.py
manilaclient/osc/v2/share_network_subnets.py
manilaclient/osc/v2/share_networks.py
manilaclient/osc/v2/share_pools.py
manilaclient/osc/v2/share_replica_export_locations.py
manilaclient/osc/v2/share_replicas.py
manilaclient/osc/v2/share_servers.py
manilaclient/osc/v2/share_snapshot_instance_export_locations.py
manilaclient/osc/v2/share_snapshot_instances.py
manilaclient/osc/v2/share_snapshots.py
manilaclient/osc/v2/share_transfers.py
manilaclient/osc/v2/share_type_access.py
manilaclient/osc/v2/share_types.py
manilaclient/osc/v2/data/manila.csv
manilaclient/tests/__init__.py
manilaclient/tests/functional/__init__.py
manilaclient/tests/functional/base.py
manilaclient/tests/functional/client.py
manilaclient/tests/functional/exceptions.py
python_manilaclient-5.7.1.dist-info/licenses/AUTHORS
python_manilaclient-5.7.1.dist-info/licenses/LICENSE
python_manilaclient-5.7.1.dist-info/METADATA
python_manilaclient-5.7.1.dist-info/WHEEL
python_manilaclient-5.7.1.dist-info/entry_points.txt
python_manilaclient-5.7.1.dist-info/pbr.json
python_manilaclient-5.7.1.dist-info/top_level.txt
python_manilaclient-5.7.1.dist-info/RECORD
