Metadata-Version: 2.4
Name: python-manilaclient
Version: 5.7.1
Summary: Client library for OpenStack Shared File System Storage
Author-email: OpenStack <openstack-discuss@lists.openstack.org>
License: Apache-2.0
Project-URL: Homepage, https://docs.openstack.org/python-manilaclient/
Project-URL: Repository, https://opendev.org/openstack/python-manilaclient/
Classifier: Environment :: OpenStack
Classifier: Intended Audience :: Information Technology
Classifier: Intended Audience :: System Administrators
Classifier: License :: OSI Approved :: Apache Software License
Classifier: Operating System :: POSIX :: Linux
Classifier: Programming Language :: Python
Classifier: Programming Language :: Python :: 3
Classifier: Programming Language :: Python :: 3.10
Classifier: Programming Language :: Python :: 3.11
Classifier: Programming Language :: Python :: 3.12
Classifier: Programming Language :: Python :: 3.13
Requires-Python: >=3.10
License-File: LICENSE
License-File: AUTHORS
Requires-Dist: pbr>=3.0.0
Requires-Dist: oslo.config>=5.2.0
Requires-Dist: oslo.log>=3.36.0
Requires-Dist: oslo.serialization>=2.20.0
Requires-Dist: oslo.utils>=3.33.0
Requires-Dist: PrettyTable>=0.7.1
Requires-Dist: requests>=2.14.2
Requires-Dist: osc-lib>=3.2.0
Requires-Dist: python-keystoneclient>=3.8.0
Requires-Dist: debtcollector>=1.2.0
Dynamic: license-file
Dynamic: requires-dist
